pyriemann_qiskit/__init__.py
pyriemann_qiskit/_version.py
pyriemann_qiskit/autoencoders.py
pyriemann_qiskit/ensemble.py
pyriemann_qiskit/pipelines.py
pyriemann_qiskit/classification/__init__.py
pyriemann_qiskit/classification/algorithms.py
pyriemann_qiskit/classification/wrappers.py
pyriemann_qiskit/datasets/__init__.py
pyriemann_qiskit/datasets/utils.py
pyriemann_qiskit/utils/__init__.py
pyriemann_qiskit/utils/distance.py
pyriemann_qiskit/utils/docplex.py
pyriemann_qiskit/utils/filtering.py
pyriemann_qiskit/utils/firebase_cert.py
pyriemann_qiskit/utils/firebase_connector.py
pyriemann_qiskit/utils/hyper_params_factory.py
pyriemann_qiskit/utils/math.py
pyriemann_qiskit/utils/mean.py
pyriemann_qiskit/utils/preprocessing.py
pyriemann_qiskit/utils/quantum_provider.py
pyriemann_qiskit/utils/utils.py
pyriemann_qiskit/visualization/__init__.py
pyriemann_qiskit/visualization/art.py
pyriemann_qiskit/visualization/manifold.py
pyriemann_qiskit-0.4.2.dist-info/licenses/LICENSE
pyriemann_qiskit-0.4.2.dist-info/METADATA
pyriemann_qiskit-0.4.2.dist-info/WHEEL
pyriemann_qiskit-0.4.2.dist-info/top_level.txt
pyriemann_qiskit-0.4.2.dist-info/RECORD
