Metadata-Version: 2.4
Name: pyriemann-qiskit
Version: 0.4.2
Summary: Qiskit wrapper for pyRiemann
Home-page: https://pyriemann-qiskit.readthedocs.io
Author: Gregoire Cattan
Author-email: gcattan@hotmail.com
License: BSD (3-clause)
Project-URL: Documentation, https://pyriemann-qiskit.readthedocs.io/
Project-URL: Source, https://github.com/pyRiemann/pyRiemann-qiskit
Project-URL: Tracker, https://github.com/pyRiemann/pyRiemann-qiskit/issues/
Platform: any
Requires-Python: >=3.10
License-File: LICENSE
Requires-Dist: numpy<2.3
Requires-Dist: cython
Requires-Dist: pyriemann==0.7
Requires-Dist: qiskit==1.*
Requires-Dist: qiskit_algorithms==0.3.1
Requires-Dist: qiskit_machine_learning==0.7.2
Requires-Dist: qiskit_ibm_runtime==0.34.0
Requires-Dist: qiskit-optimization==0.6.1
Requires-Dist: qiskit-aer==0.17.0
Requires-Dist: cvxpy==1.6.5
Requires-Dist: scipy==1.13.1
Requires-Dist: docplex==2.29.245
Requires-Dist: firebase_admin==6.8.0
Requires-Dist: scikit-learn==1.5.2
Requires-Dist: tqdm
Requires-Dist: pandas
Provides-Extra: docs
Requires-Dist: sphinx-gallery; extra == "docs"
Requires-Dist: sphinx-bootstrap_theme; extra == "docs"
Requires-Dist: numpydoc; extra == "docs"
Requires-Dist: mne==1.9.0; extra == "docs"
Requires-Dist: mne-bids==0.16.0; extra == "docs"
Requires-Dist: seaborn>=0.12.1; extra == "docs"
Requires-Dist: moabb==1.2.0; extra == "docs"
Requires-Dist: imbalanced-learn==0.12.4; extra == "docs"
Provides-Extra: tests
Requires-Dist: pytest; extra == "tests"
Requires-Dist: seaborn; extra == "tests"
Requires-Dist: flake8; extra == "tests"
Requires-Dist: mne; extra == "tests"
Requires-Dist: pooch; extra == "tests"
Provides-Extra: optim
Requires-Dist: qiskit-symb==0.2.0; extra == "optim"
Requires-Dist: symengine==0.11.0; extra == "optim"
Provides-Extra: optim-linux
Requires-Dist: qiskit-aer-gpu==0.15.1; extra == "optim-linux"
Dynamic: author
Dynamic: author-email
Dynamic: description
Dynamic: description-content-type
Dynamic: home-page
Dynamic: license
Dynamic: license-file
Dynamic: platform
Dynamic: project-url
Dynamic: provides-extra
Dynamic: requires-dist
Dynamic: requires-python
Dynamic: summary
